{
  "categories": [
    {
      "title": "Programming Languages",
      "icon": "Code",
      "color": "primary",
      "skills": [
        { "name": "Python", "level": 90, "description": "Advanced scripting and AI development" },
        { "name": "JavaScript", "level": 85, "description": "Modern ES6+ and frameworks" },
        { "name": "HTML/CSS", "level": 95, "description": "Semantic markup and advanced styling" },
        { "name": "SQL", "level": 80, "description": "Database design and optimization" },
        { "name": "PHP", "level": 75, "description": "Server-side development" }
      ]
    },
    {
      "title": "Frameworks & Libraries",
      "icon": "Settings",
      "color": "secondary",
      "skills": [
        { "name": "React", "level": 85, "description": "Component-based UI development" },
        { "name": "Node.js", "level": 80, "description": "Server-side JavaScript runtime" },
        { "name": "Express", "level": 75, "description": "Web application framework" },
        { "name": "Next.js", "level": 70, "description": "Full-stack React framework" }
      ]
    },
    {
      "title": "Databases & AI/ML",
      "icon": "Database",
      "color": "accent",
      "skills": [
        { "name": "MySQL", "level": 85, "description": "Relational database management" },
        { "name": "PostgreSQL", "level": 80, "description": "Advanced SQL database" },
        { "name": "VectorDB", "level": 75, "description": "Vector database for AI applications" },
        { "name": "Hugging Face", "level": 85, "description": "AI model deployment and fine-tuning" },
        { "name": "LLaMA 4", "level": 80, "description": "Large language model implementation" },
        { "name": "PEFT Fine-tuning", "level": 75, "description": "Parameter-efficient fine-tuning" }
      ]
    },
    {
      "title": "Creative & Security Tools",
      "icon": "Palette",
      "color": "highlight",
      "skills": [
        { "name": "After Effects", "level": 95, "description": "Motion graphics and visual effects" },
        { "name": "Photoshop", "level": 90, "description": "Digital image editing and design" },
        { "name": "Premiere Pro", "level": 88, "description": "Professional video editing" },
        { "name": "Illustrator", "level": 80, "description": "Vector graphics and illustration" },
        { "name": "Figma", "level": 85, "description": "UI/UX design and prototyping" },
        { "name": "Ethical Hacking", "level": 70, "description": "Cybersecurity and penetration testing" },
        { "name": "iPhone Jailbreak", "level": 75, "description": "iOS system modification" }
      ]
    },
    {
      "title": "Development Tools",
      "icon": "Wrench",
      "color": "primary",
      "skills": [
        { "name": "Git & GitHub", "level": 90, "description": "Version control and collaboration" },
        { "name": "Docker", "level": 75, "description": "Containerization and deployment" },
        { "name": "Linux", "level": 80, "description": "System administration and scripting" },
        { "name": "Arduino", "level": 70, "description": "IoT and embedded systems" },
        { "name": "Postman", "level": 85, "description": "API testing and development" }
      ]
    }
  ],
  "currentFocus": "Currently working on Hugging Face with LLaMA 4 model, experimenting with PEFT fine-tuning, building a personal AI system."
}